smstools/__init__.py
smstools/api_client.py
smstools/api_response.py
smstools/configuration.py
smstools/exceptions.py
smstools/py.typed
smstools/rest.py
smstools/smstools.py
smstools/api/__init__.py
smstools/api/default_api.py
smstools/models/__init__.py
smstools/models/account_response.py
smstools/models/balance_response.py
smstools/models/contact.py
smstools/models/contact_info.py
smstools/models/contact_info_create_request.py
smstools/models/contact_info_request.py
smstools/models/contact_info_response.py
smstools/models/contact_info_update_request.py
smstools/models/contact_response.py
smstools/models/create_group200_response.py
smstools/models/create_group_request.py
smstools/models/create_message_template_request.py
smstools/models/create_optout_request.py
smstools/models/create_subaccount_request.py
smstools/models/error_response.py
smstools/models/format_number200_response.py
smstools/models/format_number200_response_inner.py
smstools/models/format_number_request.py
smstools/models/get_conversation200_response.py
smstools/models/get_conversation200_response_all_of_conversation_inner.py
smstools/models/get_conversation200_response_all_of_conversation_inner_file.py
smstools/models/get_country_codes200_response_inner.py
smstools/models/get_group200_response.py
smstools/models/get_group200_response_contacts_inner.py
smstools/models/get_group200_response_groupinfo.py
smstools/models/get_history200_response.py
smstools/models/get_history200_response_all_of_messages_inner.py
smstools/models/get_history200_response_all_of_messages_inner_response.py
smstools/models/get_inbox200_response.py
smstools/models/get_inbox200_response_all_of_messages_inner.py
smstools/models/get_outbox200_response.py
smstools/models/get_specific_inbox200_response.py
smstools/models/get_specific_inbox200_response_all_of_messages_inner.py
smstools/models/get_webhook200_response_inner.py
smstools/models/get_webhook200_response_inner_message.py
smstools_api_client-0.0.9.dist-info/METADATA
smstools_api_client-0.0.9.dist-info/WHEEL
smstools_api_client-0.0.9.dist-info/top_level.txt
smstools_api_client-0.0.9.dist-info/RECORD
