Metadata-Version: 2.1
Name: smstools-api-client
Version: 0.0.9
Summary: Smstools API
Home-page: https://github.com/pvda-ptb/smstools-openapi-python
Author: David Danssaert
Author-email: OpenAPI Generator Community <team@openapitools.org>
License: NoLicense
Project-URL: Repository, https://github.com/GIT_USER_ID/GIT_REPO_ID
Keywords: OpenAPI,OpenAPI-Generator,Smstools API
Requires-Python: >=3.7
Requires-Dist: urllib3<3.0.0,>=2.1.0
Requires-Dist: python-dateutil>=2.8.2
Requires-Dist: pydantic>=2
Requires-Dist: typing-extensions>=4.7.1
